MANIFEST.in
README.md
pypi_long_description.md
setup.py
progestimator/__init__.py
progestimator/prog_regression.py
scikit_learn_progestimator.egg-info/PKG-INFO
scikit_learn_progestimator.egg-info/SOURCES.txt
scikit_learn_progestimator.egg-info/dependency_links.txt
scikit_learn_progestimator.egg-info/requires.txt
scikit_learn_progestimator.egg-info/top_level.txt